README.md
pyproject.toml
setup.cfg
setup.py
spacetower_orbit_extrapolation_python_client/__init__.py
spacetower_orbit_extrapolation_python_client/api_client.py
spacetower_orbit_extrapolation_python_client/api_response.py
spacetower_orbit_extrapolation_python_client/configuration.py
spacetower_orbit_extrapolation_python_client/exceptions.py
spacetower_orbit_extrapolation_python_client/py.typed
spacetower_orbit_extrapolation_python_client/rest.py
spacetower_orbit_extrapolation_python_client.egg-info/PKG-INFO
spacetower_orbit_extrapolation_python_client.egg-info/SOURCES.txt
spacetower_orbit_extrapolation_python_client.egg-info/dependency_links.txt
spacetower_orbit_extrapolation_python_client.egg-info/requires.txt
spacetower_orbit_extrapolation_python_client.egg-info/top_level.txt
spacetower_orbit_extrapolation_python_client/api/__init__.py
spacetower_orbit_extrapolation_python_client/api/default_api.py
spacetower_orbit_extrapolation_python_client/models/__init__.py
spacetower_orbit_extrapolation_python_client/models/anomaly_type.py
spacetower_orbit_extrapolation_python_client/models/atmosphere_model.py
spacetower_orbit_extrapolation_python_client/models/atmosphere_type.py
spacetower_orbit_extrapolation_python_client/models/atmospheric_drag_perturbation.py
spacetower_orbit_extrapolation_python_client/models/attitude_based_finite_thrust_schedule.py
spacetower_orbit_extrapolation_python_client/models/attitude_ephemeris.py
spacetower_orbit_extrapolation_python_client/models/attitude_ephemeris_request.py
spacetower_orbit_extrapolation_python_client/models/attitude_law.py
spacetower_orbit_extrapolation_python_client/models/attitude_law_type.py
spacetower_orbit_extrapolation_python_client/models/attitude_representation_type.py
spacetower_orbit_extrapolation_python_client/models/attitude_sequence.py
spacetower_orbit_extrapolation_python_client/models/attitude_sequence_type.py
spacetower_orbit_extrapolation_python_client/models/battery_model.py
spacetower_orbit_extrapolation_python_client/models/battery_power_ephemeris.py
spacetower_orbit_extrapolation_python_client/models/battery_power_ephemeris_request.py
spacetower_orbit_extrapolation_python_client/models/box_geometry.py
spacetower_orbit_extrapolation_python_client/models/box_object.py
spacetower_orbit_extrapolation_python_client/models/box_object_base.py
